cythondemo/__init__.py
cythondemo/tree/__init__.py
cythondemo/tree/ctree.cpython-36m-x86_64-linux-gnu.so
cythondemo/config/__init__.py
cythondemo/config/meta.py
cythondemo/math/math.py
cythondemo/math/__init__.py
cythondemo/math/cmath.cpython-36m-x86_64-linux-gnu.so
cython_demo-0.0.2.dist-info/METADATA
cython_demo-0.0.2.dist-info/WHEEL
cython_demo-0.0.2.dist-info/top_level.txt
cython_demo-0.0.2.dist-info/RECORD
cython_demo-0.0.2.dist-info/LICENSE
