Metadata-Version: 2.1
Name: cython-demo
Version: 0.0.2
Summary: A releasable demo for cython.
Home-page: https://github.com/HansBug/cython-demo
Author: HansBug
Author-email: hansbug@buaa.edu.cn
License: Apache License, Version 2.0
Keywords: Tree-structured Value Management
Platform: UNKNOWN
Classifier: Development Status :: 5 - Production/Stable
Classifier: Intended Audience :: Developers
Classifier: License :: OSI Approved :: Apache Software License
Classifier: Programming Language :: Python
Classifier: Programming Language :: Python :: 3
Classifier: Programming Language :: Python :: 3.6
Classifier: Programming Language :: Python :: 3.7
Classifier: Programming Language :: Python :: 3.8
Classifier: Programming Language :: Python :: 3.9
Classifier: Programming Language :: Python :: Implementation :: PyPy
Requires-Python: >=3.6
License-File: LICENSE
Requires-Dist: graphviz (~=0.17)
Requires-Dist: dill (~=0.3.4)
Provides-Extra: build
Requires-Dist: cython (>=0.29) ; extra == 'build'
Requires-Dist: build (>=0.7.0) ; extra == 'build'
Requires-Dist: auditwheel (>=4) ; extra == 'build'
Provides-Extra: test
Requires-Dist: coverage (>=5) ; extra == 'test'
Requires-Dist: mock (>=4.0.3) ; extra == 'test'
Requires-Dist: flake8 (~=3.5) ; extra == 'test'
Requires-Dist: pytest (~=5.4.3) ; extra == 'test'
Requires-Dist: pytest-cov (~=2.10.1) ; extra == 'test'
Requires-Dist: pytest-mock (~=3.5.1) ; extra == 'test'
Requires-Dist: pytest-forked (~=1.3.0) ; extra == 'test'
Requires-Dist: pytest-xdist (~=1.34.0) ; extra == 'test'
Requires-Dist: pytest-timeout (~=1.4.2) ; extra == 'test'
Requires-Dist: pytest-rerunfailures (~=9.1.1) ; extra == 'test'
Requires-Dist: easydict (<2,>=1.7) ; extra == 'test'
